{ "compressionlevel":-1,
 "height":20,
 "infinite":false,
 "layers":[
        {
         "data":[0, 0, 0, 0, 0, 0, 0, 0, 0, 0, 0, 0, 0, 0, 0, 0, 0, 0, 0, 0, 0, 0, 0, 0, 0, 0, 0, 0, 0, 0, 0, 0, 0, 0, 0, 0, 0, 0, 0, 0, 0, 0, 0, 0, 0, 0, 0, 0, 0, 0, 0, 0, 0, 0, 0, 0, 0, 0, 0, 0, 0, 0, 0, 0, 0, 0, 0, 0, 0, 0, 0, 0, 0, 0, 0, 0, 0, 0, 0, 0, 0, 0, 0, 0, 0, 0, 0, 0, 0, 0, 0, 0, 0, 0, 0, 0, 0, 0, 0, 0, 0, 0, 0, 0, 0, 0, 0, 0, 0, 0, 0, 0, 0, 0, 0, 0, 0, 0, 0, 0, 0, 0, 0, 0, 0, 0, 0, 0, 0, 0, 0, 0, 0, 0, 0, 0, 0, 0, 0, 0, 0, 0, 0, 0, 0, 0, 0, 0, 0, 0, 0, 0, 0, 0, 0, 0, 0, 0, 0, 0, 0, 0, 0, 0, 0, 0, 0, 0, 0, 0, 0, 0, 0, 0, 0, 0, 0, 0, 0, 0, 0, 0, 0, 0, 0, 0, 0, 0, 0, 0, 0, 0, 0, 0, 0, 0, 0, 0, 0, 0, 0, 0, 0, 0, 0, 0, 0, 0, 0, 0, 0, 0, 0, 0, 0, 0, 0, 0, 0, 0, 0, 0, 0, 0, 0, 0, 0, 0, 0, 0, 0, 0, 0, 0, 0, 0, 0, 0, 0, 0, 0, 0, 0, 0, 0, 0, 0, 0, 0, 0, 0, 0, 0, 0, 0, 0, 0, 0, 0, 0, 0, 0, 0, 0, 0, 0, 0, 0, 0, 0, 0, 0, 0, 0, 0, 0, 0, 0, 0, 0, 0, 0, 0, 0, 0, 0, 0, 0, 0, 0, 0, 0, 0, 0, 0, 0, 0, 0, 0, 0, 0, 0, 0, 0, 0, 0, 0, 0, 0, 0, 0, 0, 0, 0, 0, 0, 0, 0, 0, 0, 0, 0, 0, 0, 0, 0, 0, 0, 0, 0, 0, 0, 0, 0, 0, 0, 0, 0, 0, 0, 0, 0, 0, 0, 0, 0, 0, 0, 0, 0, 1121, 1121, 0, 0, 0, 0, 0, 0, 0, 0],
         "height":20,
         "id":6,
         "name":"exit",
         "opacity":1,
         "properties":[
                {
                 "name":"exitUrl",
                 "type":"string",
                 "value":"main.json#startgarage"
                }],
         "type":"tilelayer",
         "visible":true,
         "width":18,
         "x":0,
         "y":0
        }, 
        {
         "data":[0, 0, 0, 0, 0, 0, 0, 0, 0, 0, 0, 0, 0, 0, 0, 0, 0, 0, 0, 0, 0, 0, 0, 0, 0, 0, 0, 0, 0, 0, 0, 0, 0, 0, 0, 0, 0, 0, 0, 0, 0, 0, 0, 0, 0, 0, 0, 0, 0, 0, 0, 0, 0, 0, 0, 0, 0, 0, 0, 0, 0, 0, 0, 0, 0, 0, 0, 0, 0, 0, 0, 0, 0, 0, 0, 0, 0, 0, 0, 0, 0, 0, 0, 0, 0, 0, 0, 0, 0, 0, 0, 0, 0, 0, 0, 0, 0, 0, 0, 0, 0, 0, 0, 0, 0, 0, 0, 0, 0, 0, 0, 0, 0, 0, 0, 0, 0, 0, 0, 0, 0, 0, 0, 0, 0, 0, 0, 0, 0, 0, 0, 0, 0, 0, 0, 0, 0, 0, 0, 0, 0, 0, 0, 0, 0, 0, 0, 0, 0, 0, 0, 0, 0, 0, 0, 0, 0, 0, 0, 0, 0, 0, 0, 0, 0, 0, 0, 0, 0, 0, 0, 0, 0, 0, 0, 0, 0, 0, 0, 0, 0, 0, 0, 0, 0, 0, 0, 0, 0, 0, 0, 0, 0, 0, 0, 0, 0, 0, 0, 0, 0, 0, 0, 0, 0, 0, 0, 0, 0, 0, 0, 0, 0, 0, 0, 0, 0, 0, 0, 0, 0, 0, 0, 0, 0, 0, 0, 0, 0, 0, 0, 0, 0, 0, 0, 0, 0, 0, 0, 0, 0, 0, 0, 0, 0, 0, 0, 0, 0, 0, 0, 0, 0, 0, 0, 0, 0, 0, 0, 0, 0, 0, 0, 0, 0, 0, 0, 0, 0, 0, 0, 0, 0, 0, 0, 0, 0, 0, 0, 0, 0, 0, 0, 0, 0, 0, 0, 0, 0, 0, 0, 0, 0, 0, 0, 0, 0, 0, 0, 0, 0, 0, 0, 0, 0, 0, 0, 0, 0, 0, 0, 0, 0, 0, 0, 0, 0, 0, 0, 0, 0, 0, 0, 0, 0, 0, 0, 0, 0, 0, 0, 0, 1122, 1122, 0, 0, 0, 0, 0, 0, 0, 0, 0, 0, 0, 0, 0, 0, 0, 0, 0, 0, 0, 0, 0, 0, 0, 0, 0, 0],
         "height":20,
         "id":4,
         "name":"start",
         "opacity":1,
         "type":"tilelayer",
         "visible":true,
         "width":18,
         "x":0,
         "y":0
        }, 
        {
         "data":[0, 0, 0, 0, 0, 0, 0, 0, 0, 0, 0, 0, 0, 0, 0, 0, 0, 0, 0, 0, 0, 0, 0, 0, 0, 0, 0, 0, 0, 0, 0, 0, 0, 0, 0, 0, 0, 0, 0, 0, 0, 0, 0, 0, 0, 0, 0, 0, 0, 0, 0, 0, 0, 0, 0, 0, 0, 0, 0, 0, 0, 0, 0, 0, 0, 0, 0, 0, 0, 0, 0, 0, 0, 0, 0, 0, 0, 0, 0, 0, 0, 0, 0, 0, 0, 0, 0, 0, 0, 0, 0, 0, 0, 0, 0, 0, 0, 0, 0, 0, 0, 0, 0, 0, 0, 0, 0, 0, 0, 0, 0, 0, 0, 0, 0, 0, 0, 0, 0, 0, 0, 0, 0, 0, 0, 0, 0, 0, 0, 0, 0, 0, 0, 0, 0, 0, 0, 0, 0, 0, 0, 0, 0, 0, 0, 0, 0, 0, 0, 0, 0, 0, 0, 0, 0, 0, 0, 0, 0, 0, 0, 0, 0, 0, 0, 0, 0, 0, 0, 0, 0, 0, 0, 0, 0, 0, 0, 0, 0, 0, 0, 0, 0, 0, 0, 0, 0, 0, 0, 0, 0, 0, 0, 0, 0, 0, 0, 1121, 0, 0, 0, 0, 0, 0, 0, 0, 0, 0, 0, 0, 0, 0, 0, 0, 0, 0, 0, 0, 0, 0, 0, 0, 0, 0, 0, 0, 0, 0, 0, 0, 0, 0, 0, 0, 0, 0, 0, 0, 0, 0, 0, 0, 0, 0, 0, 0, 0, 0, 0, 0, 0, 0, 0, 0, 0, 0, 0, 0, 0, 0, 0, 0, 0, 0, 0, 0, 0, 0, 0, 0, 0, 0, 0, 0, 0, 0, 0, 0, 0, 0, 0, 0, 0, 0, 0, 0, 0, 0, 0, 0, 0, 0, 0, 0, 0, 0, 0, 0, 0, 0, 0, 0, 0, 0, 0, 0, 0, 0, 0, 0, 0, 0, 0, 0, 0, 0, 0, 0, 0, 0, 0, 0, 0, 0, 0, 0, 0, 0, 0, 0, 0, 0, 0, 0, 0, 0, 0, 0, 0, 0, 0, 0, 0, 0, 0, 0, 0, 0, 0, 0, 0, 0, 0, 0, 0, 0, 0, 0, 0, 0],
         "height":20,
         "id":8,
         "name":"exittohouse",
         "opacity":1,
         "properties":[
                {
                 "name":"exitUrl",
                 "type":"string",
                 "value":"house_inside.json#startfromgarage"
                }],
         "type":"tilelayer",
         "visible":true,
         "width":18,
         "x":0,
         "y":0
        }, 
        {
         "data":[0, 0, 0, 0, 0, 0, 0, 0, 0, 0, 0, 0, 0, 0, 0, 0, 0, 0, 0, 0, 0, 0, 0, 0, 0, 0, 0, 0, 0, 0, 0, 0, 0, 0, 0, 0, 0, 0, 0, 0, 0, 0, 0, 0, 0, 0, 0, 0, 0, 0, 0, 0, 0, 0, 0, 0, 0, 0, 0, 0, 0, 0, 0, 0, 0, 0, 0, 0, 0, 0, 0, 0, 0, 0, 0, 0, 0, 0, 0, 0, 0, 0, 0, 0, 0, 0, 0, 0, 0, 0, 0, 0, 0, 0, 0, 0, 0, 0, 0, 0, 0, 0, 0, 0, 0, 0, 0, 0, 0, 0, 0, 0, 0, 0, 0, 0, 0, 0, 0, 0, 0, 0, 0, 0, 0, 0, 0, 0, 0, 0, 0, 0, 0, 0, 0, 0, 0, 0, 0, 0, 0, 0, 0, 0, 0, 0, 0, 0, 0, 0, 0, 0, 0, 0, 0, 0, 0, 0, 0, 0, 0, 0, 0, 0, 0, 0, 0, 0, 0, 0, 0, 0, 0, 0, 0, 0, 0, 0, 0, 0, 0, 0, 0, 0, 0, 0, 0, 0, 0, 0, 0, 0, 0, 0, 0, 0, 1122, 0, 0, 0, 0, 0, 0, 0, 0, 0, 0, 0, 0, 0, 0, 0, 0, 0, 0, 0, 0, 0, 0, 0, 0, 0, 0, 0, 0, 0, 0, 0, 0, 0, 0, 0, 0, 0, 0, 0, 0, 0, 0, 0, 0, 0, 0, 0, 0, 0, 0, 0, 0, 0, 0, 0, 0, 0, 0, 0, 0, 0, 0, 0, 0, 0, 0, 0, 0, 0, 0, 0, 0, 0, 0, 0, 0, 0, 0, 0, 0, 0, 0, 0, 0, 0, 0, 0, 0, 0, 0, 0, 0, 0, 0, 0, 0, 0, 0, 0, 0, 0, 0, 0, 0, 0, 0, 0, 0, 0, 0, 0, 0, 0, 0, 0, 0, 0, 0, 0, 0, 0, 0, 0, 0, 0, 0, 0, 0, 0, 0, 0, 0, 0, 0, 0, 0, 0, 0, 0, 0, 0, 0, 0, 0, 0, 0, 0, 0, 0, 0, 0, 0, 0, 0, 0, 0, 0, 0, 0, 0, 0, 0, 0],
         "height":20,
         "id":7,
         "name":"startfromhouse",
         "opacity":1,
         "properties":[
                {
                 "name":"startLayer",
                 "type":"bool",
                 "value":true
                }],
         "type":"tilelayer",
         "visible":true,
         "width":18,
         "x":0,
         "y":0
        }, 
        {
         "data":[0, 0, 0, 0, 0, 0, 0, 0, 0, 0, 0, 0, 0, 0, 0, 0, 0, 0, 0, 0, 0, 0, 0, 0, 0, 0, 0, 0, 0, 0, 0, 0, 0, 0, 0, 0, 0, 0, 0, 0, 0, 0, 0, 0, 0, 0, 0, 0, 0, 0, 0, 0, 0, 0, 0, 0, 0, 0, 0, 0, 0, 0, 0, 0, 0, 0, 0, 0, 0, 0, 0, 0, 0, 0, 0, 0, 0, 0, 0, 0, 0, 0, 0, 0, 0, 1121, 1121, 0, 0, 0, 0, 0, 0, 0, 0, 0, 0, 0, 0, 0, 0, 0, 0, 0, 0, 0, 0, 0, 0, 0, 0, 0, 0, 0, 0, 0, 0, 0, 0, 0, 0, 0, 0, 0, 0, 0, 0, 0, 0, 0, 0, 0, 0, 0, 0, 0, 0, 0, 0, 0, 0, 0, 0, 0, 0, 0, 0, 0, 0, 0, 0, 0, 0, 0, 0, 0, 0, 0, 0, 0, 0, 0, 0, 0, 0, 0, 0, 0, 0, 0, 0, 0, 0, 0, 0, 0, 0, 0, 0, 0, 0, 0, 0, 0, 0, 0, 0, 0, 0, 0, 0, 0, 0, 0, 0, 0, 0, 0, 0, 0, 0, 0, 0, 0, 0, 0, 0, 0, 0, 0, 0, 0, 0, 0, 0, 0, 0, 0, 0, 0, 0, 0, 0, 0, 0, 0, 0, 0, 0, 0, 0, 0, 0, 0, 0, 0, 0, 0, 0, 0, 0, 0, 0, 0, 0, 0, 0, 0, 0, 0, 0, 0, 0, 0, 0, 0, 0, 0, 0, 0, 0, 0, 0, 0, 0, 0, 0, 0, 0, 0, 0, 0, 0, 0, 0, 0, 0, 0, 0, 0, 0, 0, 0, 0, 0, 0, 0, 0, 0, 0, 0, 0, 0, 0, 0, 0, 0, 0, 0, 0, 0, 0, 0, 0, 0, 0, 0, 0, 0, 0, 0, 0, 0, 0, 0, 0, 0, 0, 0, 0, 0, 0, 0, 0, 0, 0, 0, 0, 0, 0, 0, 0, 0, 0, 0, 0, 0, 0, 0, 0, 0, 0, 0, 0, 0, 0, 0, 0, 0, 0, 0, 0, 0, 0, 0, 0, 0, 0, 0, 0],
         "height":20,
         "id":14,
         "name":"exittooutside",
         "opacity":1,
         "properties":[
                {
                 "name":"exitUrl",
                 "type":"string",
                 "value":"main.json#starttogarage"
                }],
         "type":"tilelayer",
         "visible":true,
         "width":18,
         "x":0,
         "y":0
        }, 
        {
         "data":[0, 0, 0, 0, 0, 0, 0, 0, 0, 0, 0, 0, 0, 0, 0, 0, 0, 0, 0, 0, 0, 0, 0, 0, 0, 0, 0, 0, 0, 0, 0, 0, 0, 0, 0, 0, 0, 0, 0, 0, 0, 0, 0, 0, 0, 0, 0, 0, 0, 0, 0, 0, 0, 0, 0, 0, 0, 0, 0, 0, 0, 0, 0, 0, 0, 0, 0, 0, 0, 0, 0, 0, 0, 0, 0, 0, 0, 0, 0, 0, 0, 0, 0, 0, 0, 0, 0, 0, 0, 0, 0, 0, 0, 0, 0, 0, 0, 0, 0, 0, 0, 0, 0, 1122, 1122, 0, 0, 0, 0, 0, 0, 0, 0, 0, 0, 0, 0, 0, 0, 0, 0, 0, 0, 0, 0, 0, 0, 0, 0, 0, 0, 0, 0, 0, 0, 0, 0, 0, 0, 0, 0, 0, 0, 0, 0, 0, 0, 0, 0, 0, 0, 0, 0, 0, 0, 0, 0, 0, 0, 0, 0, 0, 0, 0, 0, 0, 0, 0, 0, 0, 0, 0, 0, 0, 0, 0, 0, 0, 0, 0, 0, 0, 0, 0, 0, 0, 0, 0, 0, 0, 0, 0, 0, 0, 0, 0, 1122, 0, 0, 0, 0, 0, 0, 0, 0, 0, 0, 0, 0, 0, 0, 0, 0, 0, 0, 0, 0, 0, 0, 0, 0, 0, 0, 0, 0, 0, 0, 0, 0, 0, 0, 0, 0, 0, 0, 0, 0, 0, 0, 0, 0, 0, 0, 0, 0, 0, 0, 0, 0, 0, 0, 0, 0, 0, 0, 0, 0, 0, 0, 0, 0, 0, 0, 0, 0, 0, 0, 0, 0, 0, 0, 0, 0, 0, 0, 0, 0, 0, 0, 0, 0, 0, 0, 0, 0, 0, 0, 0, 0, 0, 0, 0, 0, 0, 0, 0, 0, 0, 0, 0, 0, 0, 0, 0, 0, 0, 0, 0, 0, 0, 0, 0, 0, 0, 0, 0, 0, 0, 0, 0, 0, 0, 0, 0, 0, 0, 0, 0, 0, 0, 0, 0, 0, 0, 0, 0, 0, 0, 0, 0, 0, 0, 0, 0, 0, 0, 0, 0, 0, 0, 0, 0, 0, 0, 0, 0, 0, 0, 0, 0],
         "height":20,
         "id":13,
         "name":"startfromoutside",
         "opacity":1,
         "properties":[
                {
                 "name":"startLayer",
                 "type":"bool",
                 "value":true
                }],
         "type":"tilelayer",
         "visible":true,
         "width":18,
         "x":0,
         "y":0
        }, 
        {
         "data":[1124, 1124, 1124, 1124, 1124, 1124, 1124, 1124, 1124, 1124, 1124, 1124, 1124, 1124, 1124, 1124, 1124, 1124, 1124, 1124, 1124, 1124, 1124, 1124, 1124, 1124, 1124, 1124, 1124, 1124, 1124, 1124, 1124, 1124, 1124, 1124, 1124, 1124, 1124, 1124, 1124, 1124, 1124, 1124, 1124, 1124, 1124, 1124, 1124, 1124, 1124, 1124, 1124, 1124, 1124, 1124, 1124, 1124, 1124, 1124, 1124, 1124, 1124, 1124, 1124, 1124, 1124, 1124, 1124, 1124, 1124, 1124, 1124, 1124, 1124, 1124, 1124, 1124, 1124, 1124, 1124, 1124, 1124, 1124, 1124, 1124, 1124, 1124, 1124, 1124, 1124, 1124, 0, 0, 0, 0, 1124, 0, 0, 0, 0, 1124, 0, 0, 0, 0, 1124, 1124, 1124, 0, 0, 0, 0, 0, 0, 0, 0, 0, 0, 0, 0, 0, 0, 0, 0, 1124, 1124, 0, 0, 0, 0, 0, 0, 0, 0, 0, 0, 0, 0, 0, 0, 0, 0, 1124, 1124, 0, 0, 0, 0, 0, 0, 0, 0, 0, 0, 0, 0, 0, 0, 0, 0, 1124, 1124, 0, 0, 0, 0, 0, 0, 0, 0, 0, 0, 0, 0, 0, 0, 0, 0, 1124, 1124, 0, 0, 0, 0, 0, 0, 0, 0, 0, 0, 0, 0, 0, 0, 0, 0, 0, 1124, 0, 0, 0, 0, 0, 0, 0, 0, 0, 0, 0, 0, 0, 0, 0, 0, 1124, 1124, 0, 0, 0, 0, 0, 0, 0, 0, 0, 0, 0, 0, 0, 0, 0, 0, 1124, 1124, 0, 0, 0, 0, 0, 1124, 0, 0, 0, 0, 1124, 0, 0, 0, 0, 0, 1124, 1124, 0, 0, 0, 0, 0, 1124, 0, 0, 0, 0, 1124, 0, 0, 0, 0, 0, 1124, 1124, 0, 0, 0, 0, 0, 1124, 0, 1124, 1124, 0, 1124, 0, 0, 0, 0, 0, 1124, 1124, 0, 0, 0, 0, 0, 1124, 0, 1124, 1124, 0, 1124, 0, 0, 0, 0, 0, 1124, 1124, 0, 0, 0, 0, 0, 0, 0, 1124, 1124, 0, 0, 0, 0, 0, 0, 0, 1124, 1124, 0, 0, 0, 0, 0, 0, 0, 0, 0, 0, 0, 0, 0, 0, 0, 0, 1124, 1124, 1124, 0, 0, 0, 0, 1124, 0, 0, 0, 0, 1124, 0, 0, 0, 0, 1124, 1124],
         "height":20,
         "id":5,
         "name":"blocking",
         "opacity":1,
         "type":"tilelayer",
         "visible":true,
         "width":18,
         "x":0,
         "y":0
        }, 
        {
         "data":[0, 0, 0, 0, 0, 0, 0, 0, 0, 0, 0, 0, 0, 0, 0, 0, 0, 0, 0, 0, 8, 8, 8, 8, 0, 8, 8, 8, 8, 0, 8, 8, 8, 8, 0, 0, 0, 0, 8, 8, 8, 8, 0, 8, 8, 8, 8, 0, 8, 8, 8, 8, 0, 0, 0, 0, 8, 8, 8, 8, 0, 8, 8, 8, 8, 0, 8, 8, 8, 8, 0, 0, 0, 0, 8, 8, 8, 8, 0, 8, 8, 8, 8, 0, 8, 8, 8, 8, 0, 0, 0, 0, 612, 612, 612, 612, 0, 612, 612, 612, 612, 0, 612, 612, 612, 612, 0, 0, 0, 612, 612, 612, 612, 612, 612, 612, 612, 612, 612, 612, 612, 612, 612, 612, 612, 0, 0, 612, 612, 612, 612, 612, 612, 612, 612, 612, 612, 612, 612, 612, 612, 612, 612, 0, 0, 612, 612, 612, 612, 612, 612, 612, 612, 612, 612, 612, 612, 612, 612, 612, 612, 0, 0, 612, 612, 612, 612, 612, 612, 612, 612, 612, 612, 612, 612, 612, 612, 612, 612, 0, 0, 612, 612, 612, 612, 612, 612, 612, 612, 612, 612, 612, 612, 612, 612, 612, 612, 612, 0, 612, 612, 612, 612, 612, 612, 612, 612, 612, 612, 612, 612, 612, 612, 612, 612, 0, 0, 612, 612, 612, 612, 612, 612, 612, 612, 612, 612, 612, 612, 612, 612, 612, 612, 0, 0, 612, 612, 612, 612, 612, 612, 612, 612, 612, 612, 612, 612, 612, 612, 612, 612, 0, 0, 612, 612, 612, 612, 612, 612, 612, 612, 612, 612, 612, 612, 612, 612, 612, 612, 0, 0, 612, 612, 612, 612, 612, 612, 612, 612, 612, 612, 612, 612, 612, 612, 612, 612, 0, 0, 612, 612, 612, 612, 612, 612, 612, 612, 612, 612, 612, 612, 612, 612, 612, 612, 0, 0, 612, 612, 612, 612, 612, 612, 612, 612, 612, 612, 612, 612, 612, 612, 612, 612, 0, 0, 612, 612, 612, 612, 612, 612, 612, 612, 612, 612, 612, 612, 612, 612, 612, 612, 0, 0, 0, 612, 612, 612, 612, 0, 612, 612, 612, 612, 0, 612, 612, 612, 612, 0, 0],
         "height":20,
         "id":3,
         "name":"floor",
         "opacity":1,
         "type":"tilelayer",
         "visible":true,
         "width":18,
         "x":0,
         "y":0
        }, 
        {
         "data":[1058, 1058, 1058, 1058, 1058, 1058, 1058, 1058, 1058, 1058, 1058, 1058, 1058, 1058, 1058, 1058, 1058, 1058, 1058, 931, 1134, 1135, 1136, 1137, 932, 1134, 1135, 1136, 1137, 932, 1138, 1139, 1140, 1141, 929, 1058, 1058, 931, 1151, 1152, 1153, 1154, 932, 1151, 1152, 1153, 1154, 932, 1155, 1156, 1157, 1158, 929, 1058, 1058, 931, 1168, 1169, 1170, 1171, 932, 1168, 1169, 1170, 1171, 932, 1172, 1173, 1174, 1175, 929, 1058, 1058, 931, 1185, 1186, 1187, 1188, 932, 1185, 1186, 1187, 1188, 932, 1189, 1190, 1191, 1192, 929, 1058, 1058, 947, 0, 0, 0, 0, 946, 0, 0, 0, 0, 946, 0, 0, 0, 0, 945, 1058, 1058, 0, 0, 0, 0, 0, 0, 0, 0, 0, 0, 0, 0, 0, 0, 0, 0, 1058, 1058, 0, 0, 0, 0, 0, 0, 0, 0, 0, 0, 0, 0, 0, 0, 0, 0, 1058, 1058, 0, 0, 0, 0, 0, 0, 0, 0, 0, 0, 0, 0, 0, 0, 0, 0, 930, 1058, 0, 0, 0, 0, 0, 0, 0, 0, 0, 0, 0, 0, 0, 0, 0, 0, 946, 1058, 0, 0, 0, 0, 0, 0, 0, 0, 0, 0, 0, 0, 0, 0, 0, 0, 0, 1058, 0, 0, 0, 0, 0, 0, 0, 0, 0, 0, 0, 0, 0, 0, 0, 0, 1058, 1058, 0, 0, 0, 0, 0, 0, 0, 0, 0, 0, 0, 0, 0, 0, 0, 0, 1058, 1058, 0, 0, 0, 0, 0, 0, 0, 0, 0, 0, 0, 0, 0, 0, 0, 0, 1058, 1058, 0, 0, 0, 0, 0, 0, 0, 0, 0, 0, 0, 0, 0, 0, 0, 0, 1058, 1058, 0, 0, 0, 0, 0, 0, 0, 0, 0, 0, 0, 0, 0, 0, 0, 0, 1058, 1058, 0, 0, 0, 0, 0, 0, 0, 0, 0, 0, 0, 0, 0, 0, 0, 0, 1058, 1058, 0, 0, 0, 0, 0, 0, 0, 0, 0, 0, 0, 0, 0, 0, 0, 0, 1058, 1058, 0, 0, 0, 0, 0, 0, 0, 0, 0, 0, 0, 0, 0, 0, 0, 0, 1058, 1058, 931, 0, 0, 0, 0, 932, 0, 0, 0, 0, 932, 0, 0, 0, 0, 929, 1058],
         "height":20,
         "id":1,
         "name":"wall",
         "offsetx":-1.33333333333331,
         "offsety":-5.6843418860808e-14,
         "opacity":1,
         "type":"tilelayer",
         "visible":true,
         "width":18,
         "x":0,
         "y":0
        }, 
        {
         "data":[0, 0, 0, 0, 0, 0, 0, 0, 0, 0, 0, 0, 0, 0, 0, 0, 0, 0, 0, 0, 0, 0, 0, 0, 0, 0, 0, 0, 0, 0, 0, 0, 0, 0, 0, 0, 0, 0, 0, 0, 0, 0, 0, 0, 0, 0, 0, 0, 0, 0, 0, 0, 0, 0, 0, 0, 0, 0, 0, 0, 0, 0, 0, 0, 0, 0, 0, 0, 0, 0, 0, 0, 0, 0, 0, 0, 0, 0, 0, 0, 0, 0, 0, 0, 0, 0, 0, 0, 0, 0, 0, 0, 0, 0, 0, 0, 0, 0, 0, 0, 0, 0, 0, 0, 0, 0, 0, 0, 0, 0, 0, 0, 0, 0, 0, 0, 0, 0, 0, 0, 0, 0, 0, 0, 0, 0, 0, 0, 0, 0, 0, 0, 0, 0, 0, 0, 0, 0, 0, 0, 0, 0, 0, 0, 0, 0, 0, 0, 0, 0, 0, 0, 0, 0, 0, 0, 0, 0, 0, 0, 0, 0, 0, 0, 0, 0, 0, 0, 0, 0, 0, 0, 0, 0, 0, 0, 0, 0, 0, 0, 0, 0, 0, 0, 0, 0, 0, 0, 0, 0, 0, 0, 0, 0, 0, 0, 0, 0, 0, 0, 0, 0, 0, 0, 0, 0, 0, 0, 0, 0, 0, 0, 0, 0, 0, 0, 0, 0, 0, 0, 0, 0, 0, 0, 0, 0, 0, 0, 0, 0, 0, 0, 0, 0, 0, 0, 0, 0, 0, 0, 0, 0, 0, 0, 0, 0, 0, 0, 0, 0, 0, 0, 0, 0, 0, 0, 0, 0, 0, 0, 0, 0, 0, 0, 0, 0, 0, 0, 0, 0, 0, 0, 0, 0, 0, 0, 0, 1287, 1288, 1289, 1290, 0, 0, 0, 0, 0, 0, 0, 0, 0, 0, 0, 0, 0, 0, 1304, 1305, 1306, 1307, 0, 0, 0, 0, 0, 0, 0, 0, 0, 0, 0, 0, 0, 0, 1321, 1322, 1323, 1324, 0, 0, 0, 0, 0, 0, 0, 0, 0, 0, 0, 0, 0, 0, 1338, 1339, 1340, 1341, 0, 0, 0, 0, 0, 0, 0, 0, 0, 0, 0, 0, 0, 0, 0, 0, 0, 0, 0, 0, 0, 0, 0, 0, 0],
         "height":20,
         "id":10,
         "name":"car",
         "opacity":1,
         "type":"tilelayer",
         "visible":true,
         "width":18,
         "x":0,
         "y":0
        }, 
        {
         "data":[0, 0, 0, 0, 0, 0, 0, 0, 0, 0, 0, 0, 0, 0, 0, 0, 0, 0, 0, 0, 0, 0, 0, 0, 0, 0, 0, 0, 0, 0, 0, 0, 0, 0, 0, 0, 0, 0, 0, 0, 0, 0, 0, 0, 0, 0, 0, 0, 0, 0, 0, 0, 0, 0, 0, 0, 0, 0, 0, 0, 0, 0, 0, 0, 0, 0, 0, 0, 0, 0, 0, 0, 0, 0, 0, 0, 0, 0, 0, 0, 0, 0, 0, 0, 0, 0, 0, 0, 0, 0, 0, 0, 0, 0, 0, 0, 0, 0, 0, 0, 0, 0, 0, 0, 0, 0, 0, 0, 0, 0, 0, 0, 0, 0, 0, 0, 0, 0, 0, 0, 0, 0, 0, 0, 0, 0, 0, 0, 0, 0, 0, 0, 0, 0, 0, 0, 0, 0, 0, 0, 0, 0, 0, 0, 0, 0, 0, 0, 0, 0, 0, 0, 0, 0, 0, 0, 0, 0, 0, 0, 0, 0, 0, 0, 0, 0, 0, 0, 0, 0, 0, 0, 0, 0, 0, 0, 0, 0, 0, 0, 0, 0, 0, 0, 0, 0, 0, 0, 0, 0, 0, 0, 0, 0, 0, 0, 0, 0, 0, 0, 0, 0, 0, 0, 0, 0, 0, 0, 0, 0, 0, 0, 0, 0, 0, 0, 0, 0, 0, 0, 0, 0, 2592, 0, 0, 0, 0, 2592, 0, 0, 0, 0, 0, 0, 0, 0, 0, 0, 0, 0, 2602, 0, 0, 0, 0, 2602, 0, 0, 0, 0, 0, 0, 0, 0, 0, 0, 0, 0, 2602, 0, 0, 0, 0, 2602, 0, 0, 0, 0, 0, 0, 0, 0, 0, 0, 0, 0, 2602, 0, 0, 0, 0, 2602, 0, 0, 0, 0, 0, 0, 0, 0, 0, 0, 0, 0, 2612, 0, 0, 0, 0, 2612, 0, 0, 0, 0, 0, 0, 0, 0, 0, 0, 0, 0, 0, 0, 0, 0, 0, 0, 0, 0, 0, 0, 0, 0, 0, 0, 0, 0, 0, 0, 0, 0, 0, 0, 0, 0, 0, 0, 0, 0, 0, 0, 0, 0, 0, 0, 0, 0, 0, 0, 0, 0, 0, 0, 0, 0, 0, 0, 0, 0],
         "height":20,
         "id":11,
         "name":"clothesrack",
         "opacity":1,
         "type":"tilelayer",
         "visible":true,
         "width":18,
         "x":0,
         "y":0
        }, 
        {
         "draworder":"topdown",
         "id":2,
         "name":"floorLayer",
         "objects":[],
         "opacity":1,
         "type":"objectgroup",
         "visible":true,
         "x":0,
         "y":0
        }, 
        {
         "data":[0, 0, 0, 0, 0, 0, 0, 0, 0, 0, 0, 0, 0, 0, 0, 0, 0, 0, 0, 0, 0, 0, 0, 0, 0, 0, 0, 0, 0, 0, 0, 0, 0, 0, 0, 0, 0, 0, 0, 0, 0, 0, 0, 0, 0, 0, 0, 0, 0, 0, 0, 0, 0, 0, 0, 0, 0, 0, 0, 0, 0, 0, 0, 0, 0, 0, 0, 0, 0, 0, 0, 0, 0, 0, 0, 0, 0, 0, 0, 0, 0, 0, 0, 0, 0, 0, 0, 0, 0, 0, 0, 0, 0, 0, 0, 0, 0, 0, 0, 0, 0, 0, 0, 0, 0, 0, 0, 0, 0, 0, 0, 0, 0, 0, 0, 0, 0, 0, 0, 0, 0, 0, 0, 0, 0, 0, 0, 0, 0, 0, 0, 0, 0, 0, 0, 0, 0, 0, 0, 0, 0, 0, 0, 0, 0, 0, 0, 0, 0, 0, 0, 0, 0, 0, 0, 0, 0, 0, 0, 0, 0, 0, 0, 0, 0, 0, 0, 0, 0, 0, 0, 0, 0, 0, 0, 0, 0, 0, 0, 0, 0, 0, 0, 0, 0, 0, 0, 0, 0, 0, 0, 0, 0, 0, 0, 0, 0, 0, 0, 0, 0, 0, 0, 0, 0, 0, 0, 0, 0, 0, 0, 0, 0, 0, 0, 0, 0, 0, 0, 0, 0, 0, 2592, 0, 0, 0, 0, 2592, 0, 0, 0, 0, 0, 0, 0, 0, 0, 0, 0, 0, 2602, 0, 0, 0, 0, 2602, 0, 0, 0, 0, 0, 0, 0, 0, 0, 0, 0, 0, 2602, 0, 0, 0, 0, 2602, 0, 0, 0, 0, 0, 0, 0, 0, 0, 0, 0, 0, 2602, 0, 0, 0, 0, 2602, 0, 0, 0, 0, 0, 0, 0, 0, 0, 0, 0, 0, 0, 0, 0, 0, 0, 0, 0, 0, 0, 0, 0, 0, 0, 0, 0, 0, 0, 0, 0, 0, 0, 0, 0, 0, 0, 0, 0, 0, 0, 0, 0, 0, 0, 0, 0, 0, 0, 0, 0, 0, 0, 0, 0, 0, 0, 0, 0, 0, 0, 0, 0, 0, 0, 0, 0, 0, 0, 0, 0, 0, 0, 0, 0, 0, 0, 0],
         "height":20,
         "id":9,
         "name":"clothes",
         "opacity":1,
         "type":"tilelayer",
         "visible":true,
         "width":18,
         "x":0,
         "y":0
        }],
 "nextlayerid":15,
 "nextobjectid":1,
 "orientation":"orthogonal",
 "renderorder":"right-down",
 "tiledversion":"1.7.2",
 "tileheight":32,
 "tilesets":[
        {
         "columns":16,
         "firstgid":1,
         "image":"tiles\/BaseChip_pipo_rearranged.png",
         "imageheight":2380,
         "imagewidth":544,
         "margin":1,
         "name":"BaseChip_pipo_rearranged",
         "properties":[
                {
                 "name":"tilesetCopyright",
                 "type":"string",
                 "value":"FREE (https:\/\/pipoya.itch.io\/pipoya-rpg-tileset-32x32)"
                }],
         "spacing":2,
         "tilecount":1120,
         "tileheight":32,
         "tilewidth":32,
         "transparentcolor":"#ff00ff"
        }, 
        {
         "columns":9,
         "firstgid":1121,
         "image":"tiles\/mapUtilities.png",
         "imageheight":34,
         "imagewidth":306,
         "margin":1,
         "name":"mapUtilities",
         "properties":[
                {
                 "name":"tilesetCopyright",
                 "type":"string",
                 "value":"FREE (https:\/\/github.com\/workadventure-xce\/workadventure-xce-map-starter-kit)"
                }],
         "spacing":2,
         "tilecount":9,
         "tileheight":32,
         "tiles":[
                {
                 "id":3,
                 "properties":[
                        {
                         "name":"collides",
                         "type":"bool",
                         "value":true
                        }]
                }],
         "tilewidth":32,
         "transparentcolor":"#ff00ff"
        }, 
        {
         "columns":2,
         "firstgid":1130,
         "image":"tiles\/worldExit.png",
         "imageheight":64,
         "imagewidth":64,
         "margin":0,
         "name":"worldexit",
         "properties":[
                {
                 "name":"tilesetCopyright",
                 "type":"string",
                 "value":"cc0 (https:\/\/git.cccv.de\/rc3\/world-tiles)"
                }],
         "spacing":0,
         "tilecount":4,
         "tileheight":32,
         "tilewidth":32
        }, 
        {
         "columns":17,
         "firstgid":1134,
         "image":"tiles\/cyberfirestationTiles.png",
         "imageheight":2380,
         "imagewidth":544,
         "margin":0,
         "name":"cyberfirestationTiles",
         "properties":[
                {
                 "name":"tilesetCopyright",
                 "type":"string",
                 "value":"cc0"
                }],
         "spacing":0,
         "tilecount":1258,
         "tileheight":32,
         "tilewidth":32
        }, 
        {
         "columns":10,
         "firstgid":2392,
         "image":"tiles\/cyberfirestationTiles2.png",
         "imageheight":640,
         "imagewidth":320,
         "margin":0,
         "name":"cyberfirestationTiles2",
         "properties":[
                {
                 "name":"tilesetCopyright",
                 "type":"string",
                 "value":"cc0"
                }],
         "spacing":0,
         "tilecount":200,
         "tileheight":32,
         "tilewidth":32
        }, 
        {
         "columns":10,
         "firstgid":2592,
         "image":"tiles\/cyberfirestationTiles3.png",
         "imageheight":640,
         "imagewidth":320,
         "margin":0,
         "name":"cyberfirestationTiles3",
         "spacing":0,
         "tilecount":200,
         "tileheight":32,
         "tilewidth":32
        }],
 "tilewidth":32,
 "type":"map",
 "version":"1.6",
 "width":18
}